pdf_orientation_corrector/__init__.py
pdf_orientation_corrector/main.py
pdf_orientation_corrector-0.1.4.dist-info/METADATA
pdf_orientation_corrector-0.1.4.dist-info/WHEEL
pdf_orientation_corrector-0.1.4.dist-info/RECORD
