Metadata-Version: 2.1
Name: pdf-orientation-corrector
Version: 0.1.4
Summary: A Python module to automatically detect and correct the orientation of pages in PDF documents.
Author: James Standbridge
Author-email: james.standbridge.git@gmail.com
Requires-Python: >=3.8,<4.0
Classifier: Programming Language :: Python :: 3
Classifier: Programming Language :: Python :: 3.8
Classifier: Programming Language :: Python :: 3.9
Classifier: Programming Language :: Python :: 3.10
Classifier: Programming Language :: Python :: 3.11
Classifier: Programming Language :: Python :: 3.12
Requires-Dist: Pillow (>=10.1.0,<11.0.0)
Requires-Dist: PyPDF2 (>=3.0.1,<4.0.0)
Requires-Dist: pdf2image (>=1.16.3,<2.0.0)
Requires-Dist: pytesseract (>=0.3.10,<0.4.0)
